shurjopay_plugin/__init__.py
shurjopay_plugin/logger_config.py
shurjopay_plugin/models.py
shurjopay_plugin/shurjopay_plugin.py
shurjopay_plugin/utils.py
shurjopay_plugin-0.1.9.dist-info/LICENSE
shurjopay_plugin-0.1.9.dist-info/METADATA
shurjopay_plugin-0.1.9.dist-info/WHEEL
shurjopay_plugin-0.1.9.dist-info/top_level.txt
shurjopay_plugin-0.1.9.dist-info/RECORD
