Metadata-Version: 2.1
Name: shurjopay-plugin
Version: 0.1.9
Summary: Shurjopay version 2.1 payment gateway integration package for python users
Home-page: https://github.com/shurjopay-plugins/sp-plugin-python.git
Author: Mahabubul Hasan
Author-email: plugindev@shurjomukhi.com.bd
Project-URL: Bug Tracker, https://github.com/shurjopay-plugins/sp-plugin-python/issues
Classifier: Programming Language :: Python :: 3
Classifier: License :: OSI Approved :: MIT License
Classifier: Operating System :: OS Independent
Requires-Python: >=3.7
License-File: LICENSE
